normet/__init__.py
normet/analysis/__init__.py
normet/analysis/decomposition.py
normet/analysis/normalise.py
normet/analysis/pdp.py
normet/analysis/rolling.py
normet/backends/__init__.py
normet/backends/flaml_backend.py
normet/backends/h2o_backend.py
normet/causal/__init__.py
normet/causal/_core.py
normet/causal/bands.py
normet/causal/batch.py
normet/causal/mlscm.py
normet/causal/placebo.py
normet/causal/scm.py
normet/model/__init__.py
normet/model/io.py
normet/model/predict.py
normet/model/train.py
normet/pipeline/__init__.py
normet/pipeline/do_all.py
normet/pipeline/interface.py
normet/utils/__init__.py
normet/utils/_lazy.py
normet/utils/features.py
normet/utils/logging.py
normet/utils/metrics.py
normet/utils/prepare.py
normet-0.2.3.dist-info/licenses/LICENSE
normet-0.2.3.dist-info/METADATA
normet-0.2.3.dist-info/WHEEL
normet-0.2.3.dist-info/top_level.txt
normet-0.2.3.dist-info/RECORD
