Metadata-Version: 2.4
Name: normet
Version: 0.2.3
Summary: Normalisation, Decomposition, and Counterfactual Modelling for Environmental Time-series
Author-email: Congbo Song <congbo.song@ncas.ac.uk>
License: MIT License
Project-URL: Homepage, https://github.com/normet-dev/normet-py
Project-URL: Issues, https://github.com/normet-dev/normet-py/issues
Keywords: environmental-data,time series,deweathering,normalisation,counterfactual,synthetic control,causal inference,air quality,air pollution
Classifier: Intended Audience :: Science/Research
Classifier: License :: OSI Approved :: MIT License
Classifier: Operating System :: OS Independent
Classifier: Programming Language :: Python :: 3
Classifier: Programming Language :: Python :: 3 :: Only
Classifier: Programming Language :: Python :: 3.9
Classifier: Programming Language :: Python :: 3.10
Classifier: Programming Language :: Python :: 3.11
Classifier: Programming Language :: Python :: 3.12
Classifier: Topic :: Scientific/Engineering
Classifier: Topic :: Scientific/Engineering :: Information Analysis
Classifier: Topic :: Scientific/Engineering :: Atmospheric Science
Requires-Python: >=3.9
License-File: LICENSE
Requires-Dist: numpy>=1.22
Requires-Dist: pandas>=1.5
Requires-Dist: scipy>=1.10
Requires-Dist: joblib>=1.2
Requires-Dist: matplotlib>=3.6
Provides-Extra: flaml
Requires-Dist: flaml>=2.1; extra == "flaml"
Provides-Extra: h2o
Requires-Dist: h2o>=3.44; extra == "h2o"
Provides-Extra: all
Requires-Dist: flaml>=2.1; extra == "all"
Requires-Dist: h2o>=3.44; extra == "all"
Dynamic: license-file
